disclosure_extractor/__init__.py
disclosure_extractor/calculate.py
disclosure_extractor/data_processing.py
disclosure_extractor/extractor_template.json
disclosure_extractor/image_processing.py
disclosure_extractor/judicial_watch_utils.py
disclosure_extractor/post_processing.py
disclosure_extractor/jef/__init__.py
disclosure_extractor/jef/extraction.py
disclosure_extractor/jef/filters.py
disclosure_extractor/jef/utils.py
disclosure_extractor-0.0.60.dist-info/LICENSE
disclosure_extractor-0.0.60.dist-info/METADATA
disclosure_extractor-0.0.60.dist-info/WHEEL
disclosure_extractor-0.0.60.dist-info/top_level.txt
disclosure_extractor-0.0.60.dist-info/RECORD
