Metadata-Version: 2.1
Name: disclosure-extractor
Version: 0.0.60
Summary: A data extraction tool from judge financial disclosures.
Home-page: https://github.com/freelawproject/disclosure-extractor
Author: Free Law Project
Author-email: info@free.law
Maintainer: Free Law Project
Maintainer-email: info@free.law
License: BSD
Keywords: legal,financial disclosures,judiciary,ocr,document parsing
Platform: UNKNOWN
Classifier: Development Status :: 5 - Production/Stable
Classifier: Intended Audience :: Developers
Classifier: Natural Language :: English
Classifier: License :: OSI Approved :: BSD License
Classifier: Operating System :: OS Independent
Classifier: Programming Language :: Python
Classifier: Programming Language :: Python :: 3
Classifier: Programming Language :: Python :: 3.6
Classifier: Programming Language :: Python :: 3.7
Classifier: Programming Language :: Python :: 3.8
Classifier: Programming Language :: Python :: Implementation :: CPython
Classifier: Programming Language :: Python :: Implementation :: PyPy
Classifier: Topic :: Software Development :: Libraries :: Python Modules
License-File: LICENSE
Requires-Dist: chardet (>=3.0.0)
Requires-Dist: langdetect (>=1.0.9)
Requires-Dist: numpy (>=1.22.2)
Requires-Dist: opencv-python (>=4.5.5.62)
Requires-Dist: pandas (>=1.4.1)
Requires-Dist: pdf2image (>=1.16.0)
Requires-Dist: pdfminer.six (>=20211012)
Requires-Dist: pdfplumber (>=0.6.0)
Requires-Dist: pillow (>=9.0.1)
Requires-Dist: prettytable (>=3.1.1)
Requires-Dist: pyparsing (>=3.0.7)
Requires-Dist: pypdf2 (>=1.26.0)
Requires-Dist: pytesseract (>=0.3.5)
Requires-Dist: pytest (>=7.0.1)
Requires-Dist: python-dateutil (>=2.8.1)
Requires-Dist: pytz (>=2021.3)
Requires-Dist: requests (>=2.27.1)
Requires-Dist: six (>=1.16.0)
Requires-Dist: sortedcontainers (>=2.2.2)
Requires-Dist: urllib3 (>=1.25.10)
Requires-Dist: wand (>=0.6.7)
